[
  {
    "Title": "Fazer o aplicativo do papai",
    "LinkedGoalId": "",
    "Notes": "",
    "NotesMarkdown": "",
    "NoteBlocks": [
      {
        "$type": "TaskItem",
        "Title": "Planejar como sera o funcionamento do aplicativo ",
        "LinkedGoalId": "",
        "Notes": "",
        "NotesMarkdown": "",
        "NoteBlocks": [],
        "InlineTasks": [],
        "Description": "",
        "IsCompleted": false,
        "Tag": "",
        "TagColor": "Transparent",
        "CompletionPercent": 0,
        "Deadline": null,
        "Id": "ec0f0bbbbde241e4884d145b8685d29c"
      },
      {
        "$type": "TaskItem",
        "Title": "banco de dados",
        "LinkedGoalId": "",
        "Notes": "",
        "NotesMarkdown": "",
        "NoteBlocks": [],
        "InlineTasks": [],
        "Description": "",
        "IsCompleted": false,
        "Tag": "",
        "TagColor": "Transparent",
        "CompletionPercent": 0,
        "Deadline": null,
        "Id": "650ee2cffb2744d4b72e8be5a8b9b515"
      },
      {
        "$type": "TaskItem",
        "Title": "interface",
        "LinkedGoalId": "",
        "Notes": "",
        "NotesMarkdown": "",
        "NoteBlocks": [],
        "InlineTasks": [],
        "Description": "",
        "IsCompleted": false,
        "Tag": "",
        "TagColor": "Transparent",
        "CompletionPercent": 0,
        "Deadline": null,
        "Id": "f0c6f57e3ebe49d3bcc5afc142de62f9"
      },
      {
        "$type": "TaskItem",
        "Title": "gera\u00E7\u00E3o de pdfs no layout",
        "LinkedGoalId": "",
        "Notes": "",
        "NotesMarkdown": "",
        "NoteBlocks": [],
        "InlineTasks": [],
        "Description": "",
        "IsCompleted": false,
        "Tag": "",
        "TagColor": "Transparent",
        "CompletionPercent": 0,
        "Deadline": null,
        "Id": "1af89f3f86cf47709cd146967c0b2ca1"
      }
    ],
    "InlineTasks": [],
    "Description": "",
    "IsCompleted": false,
    "Tag": "Planejar",
    "TagColor": "#4CD964",
    "CompletionPercent": 0,
    "Deadline": null,
    "Id": "a5292c52cf6149df8fee1e1391191e46"
  }
]